Workbook

Sheet Director Dashboard
A1: DIRECTOR'S REMOTE DASHBOARD — 25 MAY to 5 JUN 2026
A3: Open this sheet once a day at 9:00 PM IST. Scan numbers. Send 2-3 WhatsApps. Done in 15 minutes.
A5: TODAY'S STATUS — ALL FUNCTIONS
A6: Date Today | B6: Reports Submitted | C6: Expected (6 per day) | D6: Compliance % | E6: Today's New Leads | F6: Today's Counsellings | G6: Today's Admissions | H6: Today's Collection | I6: Red Flags Open | J6: Cross-Verify Issues
A7: =TEXT(TODAY(),"dd-mmm (ddd)") -> 20-May (Wed) | B7: =COUNTA('Anjali Log'!B4:B15)+COUNTA('Samiksha Log'!B4:B15)+COUNTA('Madhu Log'!B4:B15)+COUNTA('Sowmya Log'!B4:B15)+COUNTA('Bawankar Log'!B4:B15)+COUNTA('Muzammil Log'!B4:B15) -> 0 | C7: =6*MAX(1,MIN(12,TODAY()-DATE(2026,5,24))) -> 6 | D7: =IFERROR(B7/C7,0) -> 0 | E7: =IFERROR(VLOOKUP(TODAY(),'Sowmya Log'!A:E,5,FALSE()),0) -> 0 | F7: =IFERROR(VLOOKUP(TODAY(),'Madhu Log'!A:D,4,FALSE()),0) -> 0 | G7: =IFERROR(VLOOKUP(TODAY(),'Madhu Log'!A:F,6,FALSE()),0) -> 0 | H7: =IFERROR(VLOOKUP(TODAY(),'Bawankar Log'!A:C,3,FALSE()),0) -> 0 | I7: =COUNTIF('Red Flags'!E4:E50,"Open") -> 0 | J7: =SUMPRODUCT((LEFT('Cross-Verify'!E4:E27,1)="✗")*1) -> 0
A9: DAY-WISE COMPLIANCE — DID EVERYONE REPORT?
A10: Date | B10: Day | C10: Anjali | D10: Samiksha | E10: Madhu | F10: Sowmya | G10: Bawankar | H10: Muzammil | I10: Score | J10: Notes
A11: 46167 | B11: Mon | C11: =IF(COUNTIF('Anjali Log'!B4:B25,A11)>0,"✓","") | D11: =IF(COUNTIF('Samiksha Log'!B4:B25,A11)>0,"✓","") | E11: =IF(COUNTIF('Madhu Log'!B4:B25,A11)>0,"✓","") | F11: =IF(COUNTIF('Sowmya Log'!B4:B25,A11)>0,"✓","") | G11: =IF(COUNTIF('Bawankar Log'!B4:B25,A11)>0,"✓","") | H11: =IF(COUNTIF('Muzammil Log'!B4:B25,A11)>0,"✓","") | I11: =COUNTIF(C11:H11,"✓")&"/6" -> 0/6
A12: 46168 | B12: Tue | C12: =IF(COUNTIF('Anjali Log'!B4:B25,A12)>0,"✓","") | D12: =IF(COUNTIF('Samiksha Log'!B4:B25,A12)>0,"✓","") | E12: =IF(COUNTIF('Madhu Log'!B4:B25,A12)>0,"✓","") | F12: =IF(COUNTIF('Sowmya Log'!B4:B25,A12)>0,"✓","") | G12: =IF(COUNTIF('Bawankar Log'!B4:B25,A12)>0,"✓","") | H12: =IF(COUNTIF('Muzammil Log'!B4:B25,A12)>0,"✓","") | I12: =COUNTIF(C12:H12,"✓")&"/6" -> 0/6
A13: 46169 | B13: Wed | C13: =IF(COUNTIF('Anjali Log'!B4:B25,A13)>0,"✓","") | D13: =IF(COUNTIF('Samiksha Log'!B4:B25,A13)>0,"✓","") | E13: =IF(COUNTIF('Madhu Log'!B4:B25,A13)>0,"✓","") | F13: =IF(COUNTIF('Sowmya Log'!B4:B25,A13)>0,"✓","") | G13: =IF(COUNTIF('Bawankar Log'!B4:B25,A13)>0,"✓","") | H13: =IF(COUNTIF('Muzammil Log'!B4:B25,A13)>0,"✓","") | I13: =COUNTIF(C13:H13,"✓")&"/6" -> 0/6
A14: 46170 | B14: Thu | C14: =IF(COUNTIF('Anjali Log'!B4:B25,A14)>0,"✓","") | D14: =IF(COUNTIF('Samiksha Log'!B4:B25,A14)>0,"✓","") | E14: =IF(COUNTIF('Madhu Log'!B4:B25,A14)>0,"✓","") | F14: =IF(COUNTIF('Sowmya Log'!B4:B25,A14)>0,"✓","") | G14: =IF(COUNTIF('Bawankar Log'!B4:B25,A14)>0,"✓","") | H14: =IF(COUNTIF('Muzammil Log'!B4:B25,A14)>0,"✓","") | I14: =COUNTIF(C14:H14,"✓")&"/6" -> 0/6
A15: 46171 | B15: Fri | C15: =IF(COUNTIF('Anjali Log'!B4:B25,A15)>0,"✓","") | D15: =IF(COUNTIF('Samiksha Log'!B4:B25,A15)>0,"✓","") | E15: =IF(COUNTIF('Madhu Log'!B4:B25,A15)>0,"✓","") | F15: =IF(COUNTIF('Sowmya Log'!B4:B25,A15)>0,"✓","") | G15: =IF(COUNTIF('Bawankar Log'!B4:B25,A15)>0,"✓","") | H15: =IF(COUNTIF('Muzammil Log'!B4:B25,A15)>0,"✓","") | I15: =COUNTIF(C15:H15,"✓")&"/6" -> 0/6
A16: 46172 | B16: Sat | C16: =IF(COUNTIF('Anjali Log'!B4:B25,A16)>0,"✓","") | D16: =IF(COUNTIF('Samiksha Log'!B4:B25,A16)>0,"✓","") | E16: =IF(COUNTIF('Madhu Log'!B4:B25,A16)>0,"✓","") | F16: =IF(COUNTIF('Sowmya Log'!B4:B25,A16)>0,"✓","") | G16: =IF(COUNTIF('Bawankar Log'!B4:B25,A16)>0,"✓","") | H16: =IF(COUNTIF('Muzammil Log'!B4:B25,A16)>0,"✓","") | I16: =COUNTIF(C16:H16,"✓")&"/6" -> 0/6
A17: 46173 | B17: Sun | C17: =IF(COUNTIF('Anjali Log'!B4:B25,A17)>0,"✓","") | D17: =IF(COUNTIF('Samiksha Log'!B4:B25,A17)>0,"✓","") | E17: =IF(COUNTIF('Madhu Log'!B4:B25,A17)>0,"✓","") | F17: =IF(COUNTIF('Sowmya Log'!B4:B25,A17)>0,"✓","") | G17: =IF(COUNTIF('Bawankar Log'!B4:B25,A17)>0,"✓","") | H17: =IF(COUNTIF('Muzammil Log'!B4:B25,A17)>0,"✓","") | I17: =COUNTIF(C17:H17,"✓")&"/6" -> 0/6
A18: 46174 | B18: Mon | C18: =IF(COUNTIF('Anjali Log'!B4:B25,A18)>0,"✓","") | D18: =IF(COUNTIF('Samiksha Log'!B4:B25,A18)>0,"✓","") | E18: =IF(COUNTIF('Madhu Log'!B4:B25,A18)>0,"✓","") | F18: =IF(COUNTIF('Sowmya Log'!B4:B25,A18)>0,"✓","") | G18: =IF(COUNTIF('Bawankar Log'!B4:B25,A18)>0,"✓","") | H18: =IF(COUNTIF('Muzammil Log'!B4:B25,A18)>0,"✓","") | I18: =COUNTIF(C18:H18,"✓")&"/6" -> 0/6
A19: 46175 | B19: Tue | C19: =IF(COUNTIF('Anjali Log'!B4:B25,A19)>0,"✓","") | D19: =IF(COUNTIF('Samiksha Log'!B4:B25,A19)>0,"✓","") | E19: =IF(COUNTIF('Madhu Log'!B4:B25,A19)>0,"✓","") | F19: =IF(COUNTIF('Sowmya Log'!B4:B25,A19)>0,"✓","") | G19: =IF(COUNTIF('Bawankar Log'!B4:B25,A19)>0,"✓","") | H19: =IF(COUNTIF('Muzammil Log'!B4:B25,A19)>0,"✓","") | I19: =COUNTIF(C19:H19,"✓")&"/6" -> 0/6
A20: 46176 | B20: Wed | C20: =IF(COUNTIF('Anjali Log'!B4:B25,A20)>0,"✓","") | D20: =IF(COUNTIF('Samiksha Log'!B4:B25,A20)>0,"✓","") | E20: =IF(COUNTIF('Madhu Log'!B4:B25,A20)>0,"✓","") | F20: =IF(COUNTIF('Sowmya Log'!B4:B25,A20)>0,"✓","") | G20: =IF(COUNTIF('Bawankar Log'!B4:B25,A20)>0,"✓","") | H20: =IF(COUNTIF('Muzammil Log'!B4:B25,A20)>0,"✓","") | I20: =COUNTIF(C20:H20,"✓")&"/6" -> 0/6
A21: 46177 | B21: Thu | C21: =IF(COUNTIF('Anjali Log'!B4:B25,A21)>0,"✓","") | D21: =IF(COUNTIF('Samiksha Log'!B4:B25,A21)>0,"✓","") | E21: =IF(COUNTIF('Madhu Log'!B4:B25,A21)>0,"✓","") | F21: =IF(COUNTIF('Sowmya Log'!B4:B25,A21)>0,"✓","") | G21: =IF(COUNTIF('Bawankar Log'!B4:B25,A21)>0,"✓","") | H21: =IF(COUNTIF('Muzammil Log'!B4:B25,A21)>0,"✓","") | I21: =COUNTIF(C21:H21,"✓")&"/6" -> 0/6
A22: 46178 | B22: Fri | C22: =IF(COUNTIF('Anjali Log'!B4:B25,A22)>0,"✓","") | D22: =IF(COUNTIF('Samiksha Log'!B4:B25,A22)>0,"✓","") | E22: =IF(COUNTIF('Madhu Log'!B4:B25,A22)>0,"✓","") | F22: =IF(COUNTIF('Sowmya Log'!B4:B25,A22)>0,"✓","") | G22: =IF(COUNTIF('Bawankar Log'!B4:B25,A22)>0,"✓","") | H22: =IF(COUNTIF('Muzammil Log'!B4:B25,A22)>0,"✓","") | I22: =COUNTIF(C22:H22,"✓")&"/6" -> 0/6
A24: ACTION REQUIRED FROM YOU
A25: Reports missing today (call them) | H25: =IF(D7<1,"YES — Check Day-wise grid above","All submitted") -> YES — Check Day-wise grid above
A26: Red flags awaiting your decision | H26: =COUNTIF('Red Flags'!E4:E50,"Awaiting Director") -> 0
A27: Leads with no follow-up >2 days | H27: "See Lead Tracker"
A28: Cross-verify mismatches today | H28: See Lead Tracker
A29: Pending approvals (fee waivers/refunds) | H29: =COUNTIF('Red Flags'!D4:D50,"Approval needed") -> 0
A32: THE RANKERS ACADEMY | Director's Remote Tracker | Updated automatically from staff logs

Sheet Daily Tasks
A1: PRE-ASSIGNED DAILY TASKS — EVERYONE FOLLOWS THIS
A2: These tasks run every working day, 25 May – 5 June. No deviation without Director's WhatsApp approval.
A3: Person | B3: Time | C3: Task | D3: Output Expected | E3: Verified By | F3: Priority
A4: Anjali | B4: 10:00–10:45 | C4: Check yesterday's missed calls; review Lead Tracker for fresh leads from Sowmya | D4: 5-min status note in Caller WhatsApp group | E4: Director (via Sheet) | F4: HIGH
A5: Anjali | B5: 10:45–1:00 | C5: Fresh lead calling — target 25 dials, log all in Lead Tracker | D5: Update Status column in Lead Tracker live | E5: Lead Tracker | F5: HIGH
A6: Anjali | B6: 2:00–4:00 | C6: Follow-ups on Interested + Counselling Booked leads | D6: Status changes in Lead Tracker | E6: Lead Tracker | F6: HIGH
A7: Anjali | B7: 4:00–6:00 | C7: Hot leads; book Madhu slots for confirmed prospects | D7: Counselling Calendar entries | E7: Madhu daily report | F7: HIGH
A8: Anjali | B8: 5:50–6:00 | C8: Fill her row in 'Anjali Log' sheet + send WhatsApp EOD report | D8: Daily numbers logged + WhatsApp to Director | E8: Director | F8: CRITICAL
A9: Samiksha | B9: 10:45–1:00 | C9: Follow-up on yesterday's Interested leads; re-engage old enquiries | D9: Lead Tracker updates | E9: Lead Tracker | F9: HIGH
A10: Samiksha | B10: 2:00–5:00 | C10: Re-engagement calls — old enquiry list + demo attendees | D10: 5+ status changes minimum | E10: Lead Tracker | F10: HIGH
A11: Samiksha | B11: 5:00–6:30 | C11: Evening callbacks to working parents (prime time) | D11: 3+ counsellings booked target | E11: Counselling Calendar | F11: HIGH
A12: Samiksha | B12: 6:30–6:45 | C12: Fill 'Samiksha Log' + send WhatsApp EOD report | D12: Daily numbers logged + WhatsApp to Director | E12: Director | F12: CRITICAL
A13: Madhu | B13: 10:45–12:00 | C13: Walk-in parent counselling (morning rush) | D13: Outcome logged in Counselling sheet | E13: Counselling Calendar | F13: HIGH
A14: Madhu | B14: 12:00–2:00 | C14: Scheduled counsellings booked by callers | D14: Outcome logged for each slot | E14: Counselling Calendar | F14: HIGH
... A43: Office Boy | B43: 8:00–8:30 | C43: Closing — lock-up, switch off equipment, security check | D43: Closure complete | E43: Daily | F43: CRITICAL

Sheet Anjali Log
A1: ANJALI (CALLER) — DAILY LOG
A2: Fill this row daily by 6:00 PM | Director sees this live
A3: Date | B3: Dials Made | C3: Connects | D3: Connect % | E3: Interested Leads | F3: Counsellings Booked | G3: Follow-ups Done | H3: Admissions | I3: Issues / Blockers
A4: 46167 | D4: =IFERROR(C4/B4,0) -> 0
A5: 46168 | D5: =IFERROR(C5/B5,0) -> 0
A6: 46169 | D6: =IFERROR(C6/B6,0) -> 0
A7: 46170 | D7: =IFERROR(C7/B7,0) -> 0
A8: 46171 | D8: =IFERROR(C8/B8,0) -> 0
A9: 46172 | D9: =IFERROR(C9/B9,0) -> 0
A10: 46173 | D10: =IFERROR(C10/B10,0) -> 0
A11: 46174 | D11: =IFERROR(C11/B11,0) -> 0
A12: 46175 | D12: =IFERROR(C12/B12,0) -> 0
A13: 46176 | D13: =IFERROR(C13/B13,0) -> 0
A14: 46177 | D14: =IFERROR(C14/B14,0) -> 0
A15: 46178 | D15: =IFERROR(C15/B15,0) -> 0

Sheet Samiksha Log
A1: SAMIKSHA (CALLER) — DAILY LOG
A2: Fill this row daily by 6:45 PM | Director sees this live
A3: Date | B3: Dials Made | C3: Connects | D3: Connect % | E3: Interested Leads | F3: Counsellings Booked | G3: Follow-ups Done | H3: Admissions | I3: Issues / Blockers
A4: 46167 | D4: =IFERROR(C4/B4,0) -> 0
A5: 46168 | D5: =IFERROR(C5/B5,0) -> 0
A6: 46169 | D6: =IFERROR(C6/B6,0) -> 0
A7: 46170 | D7: =IFERROR(C7/B7,0) -> 0
A8: 46171 | D8: =IFERROR(C8/B8,0) -> 0
A9: 46172 | D9: =IFERROR(C9/B9,0) -> 0
A10: 46173 | D10: =IFERROR(C10/B10,0) -> 0
A11: 46174 | D11: =IFERROR(C11/B11,0) -> 0
A12: 46175 | D12: =IFERROR(C12/B12,0) -> 0
A13: 46176 | D13: =IFERROR(C13/B13,0) -> 0
A14: 46177 | D14: =IFERROR(C14/B14,0) -> 0
A15: 46178 | D15: =IFERROR(C15/B15,0) -> 0

Sheet Madhu Log
A1: MADHU (COUNSELLOR) — DAILY LOG
A2: Fill this row daily by 6:45 PM | Director sees this live
A3: Date | B3: Walk-ins Today | C3: Scheduled Counsellings | D3: Total Done | E3: No-Shows | F3: Admissions Closed | G3: Hot Prospects for Tomorrow | H3: Notes
A4: 46167
A5: 46168
A6: 46169
A7: 46170
A8: 46171
A9: 46172
A10: 46173
A11: 46174
A12: 46175
A13: 46176
A14: 46177
A15: 46178

Sheet Sowmya Log
A1: SOWMYA (MARKETING) — DAILY LOG
A2: Fill this row daily by 7:00 PM | Director sees this live
A3: Date | B3: Field Visits | C3: Posts Published | D3: WhatsApp Broadcasts | E3: Leads Generated | F3: Tomorrow's Plan | G3: Photo Proof Sent? | H3: Notes
A4: 46167
A5: 46168
A6: 46169
A7: 46170
A8: 46171
A9: 46172
A10: 46173
A11: 46174
A12: 46175
A13: 46176
A14: 46177
A15: 46178

Sheet Bawankar Log
A1: BAWANKAR (FINANCE) — DAILY LOG
A2: Fill this row daily by 8:00 PM | Director sees this live
A3: Date | B3: Opening Cash (₹) | C3: Today's Collections (₹) | D3: Today's Expenses (₹) | E3: Closing Cash (₹) | F3: Bank Deposit (₹) | G3: Pending Dues Calls | H3: Cash Book Photo Sent? | I3: Notes
A4: 46167
A5: 46168
A6: 46169
A7: 46170
A8: 46171
A9: 46172
A10: 46173
A11: 46174
A12: 46175
A13: 46176
A14: 46177
A15: 46178

Sheet Muzammil Log
A1: MUZAMMIL (DTP) — DAILY LOG
A2: Fill this row daily by 5:45 PM | Director sees this live
A3: Date | B3: Print Jobs Done | C3: New Designs Made | D3: Pending Faculty Requests | E3: Delayed >24hr? | F3: Notes
A4: 46167
A5: 46168
A6: 46169
A7: 46170
A8: 46171
A9: 46172
A10: 46173
A11: 46174
A12: 46175
A13: 46176
A14: 46177
A15: 46178

Sheet Cross-Verify
A1: CROSS-VERIFICATION — DO REPORTS MATCH?
A2: If numbers don't match, someone reported wrong. Call them and find out.
A3: Date | B3: Check | C3: Caller Says | D3: Counsellor/Finance Says | E3: Match? | F3: Difference | G3: Action
A4: 46167 | B4: Counsellings booked | C4: =IFERROR(VLOOKUP(A4,'Anjali Log'!A:F,6,FALSE()),0)+IFERROR(VLOOKUP(A4,'Samiksha Log'!A:F,6,FALSE()),0) -> 0 | D4: =IFERROR(VLOOKUP(A4,'Madhu Log'!A:C,3,FALSE()),0) -> 0 | E4: =IF(C4=D4,"✓ MATCH","✗ MISMATCH") -> ✓ MATCH | F4: =ABS(C4-D4) -> 0 | G4: =IF(C4=D4,"OK","Call Anjali/Samiksha + Madhu") -> OK
A5: 46167 | B5: Admissions closed | C5: =IFERROR(VLOOKUP(A5,'Madhu Log'!A:F,6,FALSE()),0) -> 0 | D5: =IF(IFERROR(VLOOKUP(A5,'Bawankar Log'!A:C,3,FALSE()),0)>0,"Cash received","No cash") -> No cash | E5: =IF(AND(C5>0,D5="No cash"),"✗ MISMATCH",IF(AND(C5=0,D5="No cash"),"✓ MATCH",IF(AND(C5>0,D5="Cash received"),"✓ MATCH","⚠ Check"))) -> ✓ MATCH | F5: — | G5: =IF(LEFT(E5,1)="✓","OK","Confirm with Bawankar") -> OK
A6: 46168 | B6: Counsellings booked | C6: =IFERROR(VLOOKUP(A6,'Anjali Log'!A:F,6,FALSE()),0)+IFERROR(VLOOKUP(A6,'Samiksha Log'!A:F,6,FALSE()),0) -> 0 | D6: =IFERROR(VLOOKUP(A6,'Madhu Log'!A:C,3,FALSE()),0) -> 0 | E6: =IF(C6=D6,"✓ MATCH","✗ MISMATCH") -> ✓ MATCH | F6: =ABS(C6-D6) -> 0 | G6: =IF(C6=D6,"OK","Call Anjali/Samiksha + Madhu") -> OK
A7: 46168 | B7: Admissions closed | C7: =IFERROR(VLOOKUP(A7,'Madhu Log'!A:F,6,FALSE()),0) -> 0 | D7: =IF(IFERROR(VLOOKUP(A7,'Bawankar Log'!A:C,3,FALSE()),0)>0,"Cash received","No cash") -> No cash | E7: =IF(AND(C7>0,D7="No cash"),"✗ MISMATCH",IF(AND(C7=0,D7="No cash"),"✓ MATCH",IF(AND(C7>0,D7="Cash received"),"✓ MATCH","⚠ Check"))) -> ✓ MATCH | F7: — | G7: =IF(LEFT(E7,1)="✓","OK","Confirm with Bawankar") -> OK
A8: 46169 | B8: Counsellings booked | C8: =IFERROR(VLOOKUP(A8,'Anjali Log'!A:F,6,FALSE()),0)+IFERROR(VLOOKUP(A8,'Samiksha Log'!A:F,6,FALSE()),0) -> 0 | D8: =IFERROR(VLOOKUP(A8,'Madhu Log'!A:C,3,FALSE()),0) -> 0 | E8: =IF(C8=D8,"✓ MATCH","✗ MISMATCH") -> ✓ MATCH | F8: =ABS(C8-D8) -> 0 | G8: =IF(C8=D8,"OK","Call Anjali/Samiksha + Madhu") -> OK
A9: 46169 | B9: Admissions closed | C9: =IFERROR(VLOOKUP(A9,'Madhu Log'!A:F,6,FALSE()),0) -> 0 | D9: =IF(IFERROR(VLOOKUP(A9,'Bawankar Log'!A:C,3,FALSE()),0)>0,"Cash received","No cash") -> No cash | E9: =IF(AND(C9>0,D9="No cash"),"✗ MISMATCH",IF(AND(C9=0,D9="No cash"),"✓ MATCH",IF(AND(C9>0,D9="Cash received"),"✓ MATCH","⚠ Check"))) -> ✓ MATCH | F9: — | G9: =IF(LEFT(E9,1)="✓","OK","Confirm with Bawankar") -> OK
A10: 46170 | B10: Counsellings booked | C10: =IFERROR(VLOOKUP(A10,'Anjali Log'!A:F,6,FALSE()),0)+IFERROR(VLOOKUP(A10,'Samiksha Log'!A:F,6,FALSE()),0) -> 0 | D10: =IFERROR(VLOOKUP(A10,'Madhu Log'!A:C,3,FALSE()),0) -> 0 | E10: =IF(C10=D10,"✓ MATCH","✗ MISMATCH") -> ✓ MATCH | F10: =ABS(C10-D10) -> 0 | G10: =IF(C10=D10,"OK","Call Anjali/Samiksha + Madhu") -> OK
A11: 46170 | B11: Admissions closed | C11: =IFERROR(VLOOKUP(A11,'Madhu Log'!A:F,6,FALSE()),0) -> 0 | D11: =IF(IFERROR(VLOOKUP(A11,'Bawankar Log'!A:C,3,FALSE()),0)>0,"Cash received","No cash") -> No cash | E11: =IF(AND(C11>0,D11="No cash"),"✗ MISMATCH",IF(AND(C11=0,D11="No cash"),"✓ MATCH",IF(AND(C11>0,D11="Cash received"),"✓ MATCH","⚠ Check"))) -> ✓ MATCH | F11: — | G11: =IF(LEFT(E11,1)="✓","OK","Confirm with Bawankar") -> OK
A12: 46171 | B12: Counsellings booked | C12: =IFERROR(VLOOKUP(A12,'Anjali Log'!A:F,6,FALSE()),0)+IFERROR(VLOOKUP(A12,'Samiksha Log'!A:F,6,FALSE()),0) -> 0 | D12: =IFERROR(VLOOKUP(A12,'Madhu Log'!A:C,3,FALSE()),0) -> 0 | E12: =IF(C12=D12,"✓ MATCH","✗ MISMATCH") -> ✓ MATCH | F12: =ABS(C12-D12) -> 0 | G12: =IF(C12=D12,"OK","Call Anjali/Samiksha + Madhu") -> OK
A13: 46171 | B13: Admissions closed | C13: =IFERROR(VLOOKUP(A13,'Madhu Log'!A:F,6,FALSE()),0) -> 0 | D13: =IF(IFERROR(VLOOKUP(A13,'Bawankar Log'!A:C,3,FALSE()),0)>0,"Cash received","No cash") -> No cash | E13: =IF(AND(C13>0,D13="No cash"),"✗ MISMATCH",IF(AND(C13=0,D13="No cash"),"✓ MATCH",IF(AND(C13>0,D13="Cash received"),"✓ MATCH","⚠ Check"))) -> ✓ MATCH | F13: — | G13: =IF(LEFT(E13,1)="✓","OK","Confirm with Bawankar") -> OK
A14: 46172 | B14: Counsellings booked | C14: =IFERROR(VLOOKUP(A14,'Anjali Log'!A:F,6,FALSE()),0)+IFERROR(VLOOKUP(A14,'Samiksha Log'!A:F,6,FALSE()),0) -> 0 | D14: =IFERROR(VLOOKUP(A14,'Madhu Log'!A:C,3,FALSE()),0) -> 0 | E14: =IF(C14=D14,"✓ MATCH","✗ MISMATCH") -> ✓ MATCH | F14: =ABS(C14-D14) -> 0 | G14: =IF(C14=D14,"OK","Call Anjali/Samiksha + Madhu") -> OK
A15: 46172 | B15: Admissions closed | C15: =IFERROR(VLOOKUP(A15,'Madhu Log'!A:F,6,FALSE()),0) -> 0 | D15: =IF(IFERROR(VLOOKUP(A15,'Bawankar Log'!A:C,3,FALSE()),0)>0,"Cash received","No cash") -> No cash | E15: =IF(AND(C15>0,D15="No cash"),"✗ MISMATCH",IF(AND(C15=0,D15="No cash"),"✓ MATCH",IF(AND(C15>0,D15="Cash received"),"✓ MATCH","⚠ Check"))) -> ✓ MATCH | F15: — | G15: =IF(LEFT(E15,1)="✓","OK","Confirm with Bawankar") -> OK
A16: 46173 | B16: Counsellings booked | C16: =IFERROR(VLOOKUP(A16,'Anjali Log'!A:F,6,FALSE()),0)+IFERROR(VLOOKUP(A16,'Samiksha Log'!A:F,6,FALSE()),0) -> 0 | D16: =IFERROR(VLOOKUP(A16,'Madhu Log'!A:C,3,FALSE()),0) -> 0 | E16: =IF(C16=D16,"✓ MATCH","✗ MISMATCH") -> ✓ MATCH | F16: =ABS(C16-D16) -> 0 | G16: =IF(C16=D16,"OK","Call Anjali/Samiksha + Madhu") -> OK
A17: 46173 | B17: Admissions closed | C17: =IFERROR(VLOOKUP(A17,'Madhu Log'!A:F,6,FALSE()),0) -> 0 | D17: =IF(IFERROR(VLOOKUP(A17,'Bawankar Log'!A:C,3,FALSE()),0)>0,"Cash received","No cash") -> No cash | E17: =IF(AND(C17>0,D17="No cash"),"✗ MISMATCH",IF(AND(C17=0,D17="No cash"),"✓ MATCH",IF(AND(C17>0,D17="Cash received"),"✓ MATCH","⚠ Check"))) -> ✓ MATCH | F17: — | G17: =IF(LEFT(E17,1)="✓","OK","Confirm with Bawankar") -> OK
A18: 46174 | B18: Counsellings booked | C18: =IFERROR(VLOOKUP(A18,'Anjali Log'!A:F,6,FALSE()),0)+IFERROR(VLOOKUP(A18,'Samiksha Log'!A:F,6,FALSE()),0) -> 0 | D18: =IFERROR(VLOOKUP(A18,'Madhu Log'!A:C,3,FALSE()),0) -> 0 | E18: =IF(C18=D18,"✓ MATCH","✗ MISMATCH") -> ✓ MATCH | F18: =ABS(C18-D18) -> 0 | G18: =IF(C18=D18,"OK","Call Anjali/Samiksha + Madhu") -> OK
A19: 46174 | B19: Admissions closed | C19: =IFERROR(VLOOKUP(A19,'Madhu Log'!A:F,6,FALSE()),0) -> 0 | D19: =IF(IFERROR(VLOOKUP(A19,'Bawankar Log'!A:C,3,FALSE()),0)>0,"Cash received","No cash") -> No cash | E19: =IF(AND(C19>0,D19="No cash"),"✗ MISMATCH",IF(AND(C19=0,D19="No cash"),"✓ MATCH",IF(AND(C19>0,D19="Cash received"),"✓ MATCH","⚠ Check"))) -> ✓ MATCH | F19: — | G19: =IF(LEFT(E19,1)="✓","OK","Confirm with Bawankar") -> OK
A20: 46175 | B20: Counsellings booked | C20: =IFERROR(VLOOKUP(A20,'Anjali Log'!A:F,6,FALSE()),0)+IFERROR(VLOOKUP(A20,'Samiksha Log'!A:F,6,FALSE()),0) -> 0 | D20: =IFERROR(VLOOKUP(A20,'Madhu Log'!A:C,3,FALSE()),0) -> 0 | E20: =IF(C20=D20,"✓ MATCH","✗ MISMATCH") -> ✓ MATCH | F20: =ABS(C20-D20) -> 0 | G20: =IF(C20=D20,"OK","Call Anjali/Samiksha + Madhu") -> OK
A21: 46175 | B21: Admissions closed | C21: =IFERROR(VLOOKUP(A21,'Madhu Log'!A:F,6,FALSE()),0) -> 0 | D21: =IF(IFERROR(VLOOKUP(A21,'Bawankar Log'!A:C,3,FALSE()),0)>0,"Cash received","No cash") -> No cash | E21: =IF(AND(C21>0,D21="No cash"),"✗ MISMATCH",IF(AND(C21=0,D21="No cash"),"✓ MATCH",IF(AND(C21>0,D21="Cash received"),"✓ MATCH","⚠ Check"))) -> ✓ MATCH | F21: — | G21: =IF(LEFT(E21,1)="✓","OK","Confirm with Bawankar") -> OK
A22: 46176 | B22: Counsellings booked | C22: =IFERROR(VLOOKUP(A22,'Anjali Log'!A:F,6,FALSE()),0)+IFERROR(VLOOKUP(A22,'Samiksha Log'!A:F,6,FALSE()),0) -> 0 | D22: =IFERROR(VLOOKUP(A22,'Madhu Log'!A:C,3,FALSE()),0) -> 0 | E22: =IF(C22=D22,"✓ MATCH","✗ MISMATCH") -> ✓ MATCH | F22: =ABS(C22-D22) -> 0 | G22: =IF(C22=D22,"OK","Call Anjali/Samiksha + Madhu") -> OK
A23: 46176 | B23: Admissions closed | C23: =IFERROR(VLOOKUP(A23,'Madhu Log'!A:F,6,FALSE()),0) -> 0 | D23: =IF(IFERROR(VLOOKUP(A23,'Bawankar Log'!A:C,3,FALSE()),0)>0,"Cash received","No cash") -> No cash | E23: =IF(AND(C23>0,D23="No cash"),"✗ MISMATCH",IF(AND(C23=0,D23="No cash"),"✓ MATCH",IF(AND(C23>0,D23="Cash received"),"✓ MATCH","⚠ Check"))) -> ✓ MATCH | F23: — | G23: =IF(LEFT(E23,1)="✓","OK","Confirm with Bawankar") -> OK
A24: 46177 | B24: Counsellings booked | C24: =IFERROR(VLOOKUP(A24,'Anjali Log'!A:F,6,FALSE()),0)+IFERROR(VLOOKUP(A24,'Samiksha Log'!A:F,6,FALSE()),0) -> 0 | D24: =IFERROR(VLOOKUP(A24,'Madhu Log'!A:C,3,FALSE()),0) -> 0 | E24: =IF(C24=D24,"✓ MATCH","✗ MISMATCH") -> ✓ MATCH | F24: =ABS(C24-D24) -> 0 | G24: =IF(C24=D24,"OK","Call Anjali/Samiksha + Madhu") -> OK
A25: 46177 | B25: Admissions closed | C25: =IFERROR(VLOOKUP(A25,'Madhu Log'!A:F,6,FALSE()),0) -> 0 | D25: =IF(IFERROR(VLOOKUP(A25,'Bawankar Log'!A:C,3,FALSE()),0)>0,"Cash received","No cash") -> No cash | E25: =IF(AND(C25>0,D25="No cash"),"✗ MISMATCH",IF(AND(C25=0,D25="No cash"),"✓ MATCH",IF(AND(C25>0,D25="Cash received"),"✓ MATCH","⚠ Check"))) -> ✓ MATCH | F25: — | G25: =IF(LEFT(E25,1)="✓","OK","Confirm with Bawankar") -> OK
A26: 46178 | B26: Counsellings booked | C26: =IFERROR(VLOOKUP(A26,'Anjali Log'!A:F,6,FALSE()),0)+IFERROR(VLOOKUP(A26,'Samiksha Log'!A:F,6,FALSE()),0) -> 0 | D26: =IFERROR(VLOOKUP(A26,'Madhu Log'!A:C,3,FALSE()),0) -> 0 | E26: =IF(C26=D26,"✓ MATCH","✗ MISMATCH") -> ✓ MATCH | F26: =ABS(C26-D26) -> 0 | G26: =IF(C26=D26,"OK","Call Anjali/Samiksha + Madhu") -> OK
A27: 46178 | B27: Admissions closed | C27: =IFERROR(VLOOKUP(A27,'Madhu Log'!A:F,6,FALSE()),0) -> 0 | D27: =IF(IFERROR(VLOOKUP(A27,'Bawankar Log'!A:C,3,FALSE()),0)>0,"Cash received","No cash") -> No cash | E27: =IF(AND(C27>0,D27="No cash"),"✗ MISMATCH",IF(AND(C27=0,D27="No cash"),"✓ MATCH",IF(AND(C27>0,D27="Cash received"),"✓ MATCH","⚠ Check"))) -> ✓ MATCH | F27: — | G27: =IF(LEFT(E27,1)="✓","OK","Confirm with Bawankar") -> OK

Sheet Red Flags
A1: RED FLAGS — INCIDENTS LOG
A2: Any deviation, approval need, or unusual event logged here. Director reviews 9 PM.
A3: Date/Time | B3: Reported By | C3: Category | D3: Description | E3: Status | F3: Director's Decision

Sheet Instructions
A1: REMOTE MANAGEMENT TRACKER — HOW TO USE
A2: For Director's leave period: 25 May – 5 June 2026
A4: FOR DIRECTOR (YOU)
A5: Daily routine | B5: 9:00 PM IST — open Director Dashboard. 15 minutes max.
A6: Step 1 — Compliance check | B6: Look at 'Day-wise Compliance' grid. All 6 ticks for today? If not, call missing person.
A7: Step 2 — Cross-verify | B7: Check 'Cross-Verify Issues' count on dashboard. If >0, open the sheet and ask both people for the truth.
A8: Step 3 — Red flags | B8: Check 'Action Required From You' panel. Approve/reject pending items via WhatsApp.
A9: Step 4 — Lead pipeline | B9: Open separate Lead Tracker sheet. Note stale leads. Push specific caller next morning.
A11: FOR STAFF — DAILY EOD ROUTINE
A12: Anjali | B12: Fill 'Anjali Log' row for today by 6:00 PM. Send WhatsApp using your template card by 6:05 PM.
A13: Samiksha | B13: Fill 'Samiksha Log' by 6:45 PM. WhatsApp by 6:50 PM.
A14: Madhu | B14: Fill 'Madhu Log' by 6:45 PM. WhatsApp by 6:50 PM.
A15: Sowmya | B15: Fill 'Sowmya Log' by 7:00 PM. WhatsApp by 7:05 PM with photo proof of field visits.
A16: Bawankar | B16: Fill 'Bawankar Log' by 8:00 PM. WhatsApp by 8:05 PM WITH PHOTO of cash book.
A17: Muzammil | B17: Fill 'Muzammil Log' by 5:45 PM. WhatsApp by 5:50 PM.
A19: RULES — NON-NEGOTIABLE DURING LEAVE
A20: Rule 1 | B20: Daily Log entries are mandatory. Missed entry = phone call from Director the next morning.
A21: Rule 2 | B21: No fee waiver, refund, or discount commitment without Director's written WhatsApp approval.
A22: Rule 3 | B22: No staff leave to be granted (except medical emergency) without Director's approval.
A23: Rule 4 | B23: Cash position > ₹50,000 must be deposited same day. Photo of deposit slip to Director.
A24: Rule 5 | B24: Any unknown visitor (media, govt, vendor enquiry) — politely defer to Director's return. Note in Red Flags.
A25: Rule 6 | B25: Parent complaints — Madhu handles politely, logs in Red Flags, escalates to Director if not resolved in 30 min.
A26: Rule 7 | B26: Daily Tasks sheet defines the day. No 'mood-based' deviations. Any deviation needs Director's approval first.
A28: CROSS-VERIFY EXPLAINED
A29: What it does | B29: Auto-checks if numbers reported by different people on the same day actually match.
A30: Example 1 | B30: Anjali says she booked 3 counsellings. Madhu's log says she had 2 scheduled counsellings. MISMATCH — someone is wrong.
A31: Example 2 | B31: Madhu says 2 admissions closed today. Bawankar's collection says ₹0. MISMATCH — either no cash received OR Madhu is overstating.
A32: Why it matters | B32: It's mathematically impossible for both reports to be honest if numbers don't match. This catches both errors and inflation.
A34: EMERGENCY ESCALATION
A35: Call Director immediately for | B35: Medical emergency, fire/safety, police visit, large cash discrepancy (>₹10K), parent threat, faculty walkout.
A36: WhatsApp Director within 1 hour for | B36: Unknown visitor, refund demand, fee waiver request, complaint, IT failure affecting classes.
A37: Log in Red Flags + handle yourself | B37: Routine delays, minor parent grievances, small expenses (<₹5,000), Muzammil/Aarti issues.
